vizly_notebook/__init__.py
vizly_notebook/vizly_notebook_app.py
vizly_notebook/static/404.html
vizly_notebook/static/favicon.ico
vizly_notebook/static/favicon.png
vizly_notebook/static/index.html
vizly_notebook/static/jupyter-vega.js
vizly_notebook/static/plotly.js
vizly_notebook/static/require.2.3.4.min.js
vizly_notebook/static/_next/static/85K2Bx62df37KLmWpH0AF/_buildManifest.js
vizly_notebook/static/_next/static/85K2Bx62df37KLmWpH0AF/_ssgManifest.js
vizly_notebook/static/_next/static/chunks/175675d1-ed929c12ac9c54c1.js
vizly_notebook/static/_next/static/chunks/175675d1-ed929c12ac9c54c1.js.map
vizly_notebook/static/_next/static/chunks/468.6e42c8e4052a1187.js
vizly_notebook/static/_next/static/chunks/468.6e42c8e4052a1187.js.map
vizly_notebook/static/_next/static/chunks/4ad82c5e-4df228886a65f59e.js
vizly_notebook/static/_next/static/chunks/4ad82c5e-4df228886a65f59e.js.map
vizly_notebook/static/_next/static/chunks/4e22b678-4c4c6da658c5405a.js
vizly_notebook/static/_next/static/chunks/4e22b678-4c4c6da658c5405a.js.map
vizly_notebook/static/_next/static/chunks/639.a3b75ee08f20a0af.js
vizly_notebook/static/_next/static/chunks/639.a3b75ee08f20a0af.js.map
vizly_notebook/static/_next/static/chunks/74.d0181866c39f9037.js
vizly_notebook/static/_next/static/chunks/776.2609ea593828f042.js
vizly_notebook/static/_next/static/chunks/776.2609ea593828f042.js.map
vizly_notebook/static/_next/static/chunks/891.aab9d3640e703639.js
vizly_notebook/static/_next/static/chunks/891.aab9d3640e703639.js.map
vizly_notebook/static/_next/static/chunks/918-32845ae6d5bde960.js
vizly_notebook/static/_next/static/chunks/918-32845ae6d5bde960.js.map
vizly_notebook/static/_next/static/chunks/b5f2ed29-20581be41a534562.js
vizly_notebook/static/_next/static/chunks/b5f2ed29-20581be41a534562.js.map
vizly_notebook/static/_next/static/chunks/b637e9a5.ebfee6b48b492480.js
vizly_notebook/static/_next/static/chunks/b637e9a5.ebfee6b48b492480.js.map
vizly_notebook-0.1.28.dist-info/METADATA
vizly_notebook-0.1.28.dist-info/WHEEL
vizly_notebook-0.1.28.dist-info/entry_points.txt
vizly_notebook-0.1.28.dist-info/top_level.txt
vizly_notebook-0.1.28.dist-info/RECORD
