Metadata-Version: 2.1
Name: vizly_notebook
Version: 0.1.28
Requires-Dist: jupyter-server >=2.0
Requires-Dist: jupyter
